AUTHORS.rst
CONTRIBUTING.rst
HISTORY.rst
LICENSE
MANIFEST.in
README.rst
setup.cfg
setup.py
docs/Makefile
docs/authors.rst
docs/conf.py
docs/contributing.rst
docs/history.rst
docs/index.rst
docs/installation.rst
docs/make.bat
docs/readme.rst
docs/usage.rst
graphico/__init__.py
graphico/cli.py
graphico/graphico.py
graphico.egg-info/PKG-INFO
graphico.egg-info/SOURCES.txt
graphico.egg-info/dependency_links.txt
graphico.egg-info/entry_points.txt
graphico.egg-info/not-zip-safe
graphico.egg-info/requires.txt
graphico.egg-info/top_level.txt
tests/__init__.py
tests/test_graphico.py