Metadata-Version: 2.1
Name: graphico
Version: 0.1.0
Summary: Graph-based hierarchical consensus clustering
Home-page: https://github.com/beingkk/graphico
Author: Karlis Kanders
Author-email: kandersk@gmail.com
License: MIT license
Keywords: graphico
Platform: UNKNOWN
Classifier: Development Status :: 2 - Pre-Alpha
Classifier: Intended Audience :: Developers
Classifier: License :: OSI Approved :: MIT License
Classifier: Natural Language :: English
Classifier: Programming Language :: Python :: 3
Classifier: Programming Language :: Python :: 3.6
Classifier: Programming Language :: Python :: 3.7
Classifier: Programming Language :: Python :: 3.8
Requires-Python: >=3.6
License-File: LICENSE
License-File: AUTHORS.rst
